diixscreendata/__init__.py
diixscreendata/monitor_collector.py
diixscreendata/monitor_dll.py
diixscreendata/dll/Dix_ScreenInfo.dll
diixscreendata-0.1.1.dist-info/METADATA
diixscreendata-0.1.1.dist-info/WHEEL
diixscreendata-0.1.1.dist-info/top_level.txt
diixscreendata-0.1.1.dist-info/RECORD
