Metadata-Version: 2.4
Name: diixscreendata
Version: 0.1.1
Summary: Biblioteca Python para coletar informações e modos de monitores via DLL Dix_ScreenInfo.dll
Author: Dixavado
Classifier: Programming Language :: Python :: 3
Classifier: Operating System :: Microsoft :: Windows
Classifier: License :: OSI Approved :: MIT License
Classifier: Development Status :: 4 - Beta
Classifier: Intended Audience :: Developers
Classifier: Topic :: System :: Hardware :: Hardware Drivers
Requires-Python: >=3.7
Dynamic: author
Dynamic: classifier
Dynamic: requires-python
Dynamic: summary
